fzq_scnu/Input.py
fzq_scnu/__init__.py
fzq_scnu/change.py
fzq_scnu/constants.py
fzq_scnu/constants_download.py
fzq_scnu/fzgpio.py
fzq_scnu/fzrunner.py
fzq_scnu/fzshijue1.py
fzq_scnu/levels.py
fzq_scnu/tools.py
fzq_scnu-0.1.0.dist-info/LICENSE.txt
fzq_scnu-0.1.0.dist-info/METADATA
fzq_scnu-0.1.0.dist-info/WHEEL
fzq_scnu-0.1.0.dist-info/top_level.txt
fzq_scnu-0.1.0.dist-info/RECORD
