Metadata-Version: 2.1
Name: fzq-scnu
Version: 0.1.0
Summary: The code package for HuaGuang emulator
Home-page: https://github.com/pypa/sampleproject
Author: lxy
Author-email: 2471974739@qq.com
License: UNKNOWN
Platform: UNKNOWN
Classifier: Programming Language :: Python :: 3.7
Classifier: Programming Language :: Python :: 3.8
Classifier: Programming Language :: Python :: 3
Classifier: License :: OSI Approved :: MIT License
Classifier: Operating System :: OS Independent
Requires-Python: >=3.7, <3.9
License-File: LICENSE.txt
Requires-Dist: pygame (==1.9.6)
Requires-Dist: pgzero (==1.2.0)
